acme_tiny.py
acme_tiny-5.0.2.dist-info/licenses/LICENSE
acme_tiny-5.0.2.dist-info/METADATA
acme_tiny-5.0.2.dist-info/WHEEL
acme_tiny-5.0.2.dist-info/entry_points.txt
acme_tiny-5.0.2.dist-info/top_level.txt
acme_tiny-5.0.2.dist-info/RECORD
