Metadata-Version: 2.4
Name: acme-tiny
Version: 5.0.2
Summary: A tiny script to issue and renew TLS certs from Let's Encrypt
Author-email: Daniel Roesler <diafygi@gmail.com>
Maintainer-email: Daniel Roesler <diafygi@gmail.com>
License-Expression: MIT
Project-URL: Homepage, https://github.com/diafygi/acme-tiny
Project-URL: Documentation, https://github.com/diafygi/acme-tiny
Project-URL: Repository, https://github.com/diafygi/acme-tiny.git
Project-URL: Bug Tracker, https://github.com/diafygi/acme-tiny/issues
Classifier: Development Status :: 5 - Production/Stable
Classifier: Intended Audience :: System Administrators
Classifier: Operating System :: OS Independent
Classifier: Programming Language :: Python
Classifier: Programming Language :: Python :: 2
Classifier: Programming Language :: Python :: 2.7
Classifier: Programming Language :: Python :: 3
Classifier: Programming Language :: Python :: 3.3
Classifier: Programming Language :: Python :: 3.4
Classifier: Programming Language :: Python :: 3.5
Classifier: Programming Language :: Python :: 3.6
Classifier: Programming Language :: Python :: 3.7
Classifier: Programming Language :: Python :: 3.8
Classifier: Programming Language :: Python :: 3.9
Classifier: Programming Language :: Python :: 3.10
Classifier: Programming Language :: Python :: 3.11
Classifier: Programming Language :: Python :: 3.12
Classifier: Programming Language :: Python :: 3.13
Requires-Python: >=2.7,>=3.7
License-File: LICENSE
Dynamic: license-file
